LICENSE
README.md
setup.cfg
setup.py
aqme/__init__.py
aqme/__main__.py
aqme/aqme.py
aqme/argument_parser.py
aqme/cmin.py
aqme/filter.py
aqme/qcorr.py
aqme/qcorr_utils.py
aqme/qdescp.py
aqme/qdescp_utils.py
aqme/qprep.py
aqme/utils.py
aqme.egg-info/PKG-INFO
aqme.egg-info/SOURCES.txt
aqme.egg-info/dependency_links.txt
aqme.egg-info/requires.txt
aqme.egg-info/top_level.txt
aqme/csearch/__init__.py
aqme/csearch/base.py
aqme/csearch/crest.py
aqme/csearch/templates.py
aqme/csearch/utils.py
aqme/templates/basis_sets.csv
aqme/templates/functionals.csv
aqme/templates/template-2.sdf
aqme/templates/template-3.sdf
aqme/templates/template-4-and-5.sdf
tests/test_cmin.py
tests/test_csearch.py
tests/test_qcorr.py
tests/test_qdescp.py
tests/test_qprep.py
tests/test_utils.py