Metadata-Version: 2.4
Name: aqme
Version: 2.0.0
Summary: Automated Quantum Mechanical Environments
Home-page: https://github.com/jvalegre/aqme
Download-URL: https://github.com/jvalegre/aqme/archive/refs/tags/2.0.0.tar.gz
Author: Juan V. Alegre Requena
Author-email: jv.alegre@csic.es
License: MIT
Keywords: workflows,computational chemistry,conformational sampling,cheminformatics,quantum mechanics,DFT,automated
Classifier: Development Status :: 5 - Production/Stable
Classifier: Intended Audience :: Developers
Classifier: Topic :: Software Development :: Build Tools
Classifier: License :: OSI Approved :: MIT License
Classifier: Programming Language :: Python :: 3.11
Classifier: Programming Language :: Python :: 3.12
Classifier: Programming Language :: Python :: 3.13
Classifier: Programming Language :: Python :: 3.14
Requires-Python: >=3.11
License-File: LICENSE
Requires-Dist: PyYAML==6.0.3
Requires-Dist: pandas==2.3.3
Requires-Dist: progress==1.6.1
Requires-Dist: numpy==2.3.4
Requires-Dist: rdkit==2025.9.1
Requires-Dist: cclib==1.8.1
Requires-Dist: cffi==2.0.0
Requires-Dist: morfeus-ml==0.8.0
Dynamic: author
Dynamic: author-email
Dynamic: classifier
Dynamic: description
Dynamic: description-content-type
Dynamic: download-url
Dynamic: home-page
Dynamic: keywords
Dynamic: license
Dynamic: license-file
Dynamic: requires-dist
Dynamic: requires-python
Dynamic: summary
